[
  {
    "address": "0xDEMO_0000",
    "label": "AlphaWhale_1",
    "sourceRank": 1,
    "status": "track",
    "roi30d": 0.866,
    "consistencyScore": 0.891,
    "copyabilityScore": 0.918,
    "oneHitWonderPenalty": 0,
    "globalScore": 0.923,
    "bestCategory": "Crypto",
    "winRate30d": 0.728,
    "tradeCount30d": 1106,
    "resolvedTradeCount30d": 553,
    "averageLiquidity": 639.8697656051108,
    "averageSpread": 0.0379812025618238,
    "averageEntryTiming": 0.5423784253768362,
    "copyabilityNotes": "Good candidate — consistent, liquid, copyable",
    "riskNotes": "⚠️ High ROI may not be sustainable",
    "isDemo": true,
    "lastScannedAt": "2026-07-07T03:26:58.377Z"
  },
  {
    "address": "0xDEMO_0015",
    "label": "AlphaWhale_16",
    "sourceRank": 16,
    "status": "track",
    "roi30d": 0.848,
    "consistencyScore": 0.888,
    "copyabilityScore": 0.836,
    "oneHitWonderPenalty": 0,
    "globalScore": 0.901,
    "bestCategory": "Science",
    "winRate30d": 0.719,
    "tradeCount30d": 832,
    "resolvedTradeCount30d": 416,
    "averageLiquidity": 1064.9501100321381,
    "averageSpread": 0.011499150593462789,
    "averageEntryTiming": 0.22095316920009284,
    "copyabilityNotes": "Good candidate — consistent, liquid, copyable",
    "riskNotes": "⚠️ High ROI may not be sustainable",
    "isDemo": true,
    "lastScannedAt": "2026-07-07T03:26:58.378Z"
  },
  {
    "address": "0xDEMO_0001",
    "label": "BetMaster_2",
    "sourceRank": 2,
    "status": "track",
    "roi30d": 0.623,
    "consistencyScore": 0.872,
    "copyabilityScore": 0.904,
    "oneHitWonderPenalty": 0,
    "globalScore": 0.855,
    "bestCategory": "Sports",
    "winRate30d": 0.681,
    "tradeCount30d": 1356,
    "resolvedTradeCount30d": 678,
    "averageLiquidity": 1742.0241727042503,
    "averageSpread": 0.01800211289477411,
    "averageEntryTiming": 0.5291563948980129,
    "copyabilityNotes": "Good candidate — consistent, liquid, copyable",
    "riskNotes": "⚠️ High ROI may not be sustainable",
    "isDemo": true,
    "lastScannedAt": "2026-07-07T03:26:58.377Z"
  },
  {
    "address": "0xDEMO_0017",
    "label": "SignalTrader_18",
    "sourceRank": 18,
    "status": "track",
    "roi30d": 0.57,
    "consistencyScore": 0.86,
    "copyabilityScore": 0.855,
    "oneHitWonderPenalty": 0,
    "globalScore": 0.829,
    "bestCategory": "Politics",
    "winRate30d": 0.65,
    "tradeCount30d": 200,
    "resolvedTradeCount30d": 100,
    "averageLiquidity": 1559.2249498764145,
    "averageSpread": 0.0406515057803962,
    "averageEntryTiming": 0.2833137635613131,
    "copyabilityNotes": "Good candidate — consistent, liquid, copyable",
    "riskNotes": null,
    "isDemo": true,
    "lastScannedAt": "2026-07-07T03:26:58.378Z"
  },
  {
    "address": "0xDEMO_0002",
    "label": "SignalTrader_3",
    "sourceRank": 3,
    "status": "track",
    "roi30d": 0.53,
    "consistencyScore": 0.852,
    "copyabilityScore": 0.859,
    "oneHitWonderPenalty": 0,
    "globalScore": 0.817,
    "bestCategory": "Economics",
    "winRate30d": 0.63,
    "tradeCount30d": 1230,
    "resolvedTradeCount30d": 615,
    "averageLiquidity": 2553.419525571575,
    "averageSpread": 0.06904953211349826,
    "averageEntryTiming": 0.5465898417092464,
    "copyabilityNotes": "Good candidate — consistent, liquid, copyable",
    "riskNotes": null,
    "isDemo": true,
    "lastScannedAt": "2026-07-07T03:26:58.377Z"
  },
  {
    "address": "0xDEMO_0018",
    "label": "MarketMaven_19",
    "sourceRank": 19,
    "status": "track",
    "roi30d": 0.489,
    "consistencyScore": 0.846,
    "copyabilityScore": 0.884,
    "oneHitWonderPenalty": 0,
    "globalScore": 0.81,
    "bestCategory": "Crypto",
    "winRate30d": 0.614,
    "tradeCount30d": 712,
    "resolvedTradeCount30d": 356,
    "averageLiquidity": 1466.4625527929124,
    "averageSpread": 0.059137121273970916,
    "averageEntryTiming": 0.45735092247201325,
    "copyabilityNotes": "Good candidate — consistent, liquid, copyable",
    "riskNotes": null,
    "isDemo": true,
    "lastScannedAt": "2026-07-07T03:26:58.378Z"
  },
  {
    "address": "0xDEMO_0016",
    "label": "BetMaster_17",
    "sourceRank": 17,
    "status": "track",
    "roi30d": 0.62,
    "consistencyScore": 0.872,
    "copyabilityScore": 0.674,
    "oneHitWonderPenalty": 0,
    "globalScore": 0.808,
    "bestCategory": "Pop Culture",
    "winRate30d": 0.68,
    "tradeCount30d": 771,
    "resolvedTradeCount30d": 385,
    "averageLiquidity": 3231.555281052851,
    "averageSpread": 0.011406623060718397,
    "averageEntryTiming": 0.6809933422692307,
    "copyabilityNotes": "Good candidate — consistent, liquid, copyable",
    "riskNotes": "⚠️ High ROI may not be sustainable",
    "isDemo": true,
    "lastScannedAt": "2026-07-07T03:26:58.378Z"
  },
  {
    "address": "0xDEMO_0003",
    "label": "MarketMaven_4",
    "sourceRank": 4,
    "status": "track",
    "roi30d": 0.466,
    "consistencyScore": 0.841,
    "copyabilityScore": 0.881,
    "oneHitWonderPenalty": 0,
    "globalScore": 0.803,
    "bestCategory": "Science",
    "winRate30d": 0.603,
    "tradeCount30d": 1678,
    "resolvedTradeCount30d": 839,
    "averageLiquidity": 2470.9511805564816,
    "averageSpread": 0.06244255620817014,
    "averageEntryTiming": 0.5582797943678584,
    "copyabilityNotes": "Good candidate — consistent, liquid, copyable",
    "riskNotes": null,
    "isDemo": true,
    "lastScannedAt": "2026-07-07T03:26:58.377Z"
  },
  {
    "address": "0xDEMO_0004",
    "label": "EdgeSeeker_5",
    "sourceRank": 5,
    "status": "track",
    "roi30d": 0.422,
    "consistencyScore": 0.838,
    "copyabilityScore": 0.669,
    "oneHitWonderPenalty": 0,
    "globalScore": 0.749,
    "bestCategory": "Pop Culture",
    "winRate30d": 0.596,
    "tradeCount30d": 388,
    "resolvedTradeCount30d": 194,
    "averageLiquidity": 2148.5220885054277,
    "averageSpread": 0.019434329251969085,
    "averageEntryTiming": 0.44178960157572306,
    "copyabilityNotes": "Good candidate — consistent, liquid, copyable",
    "riskNotes": null,
    "isDemo": true,
    "lastScannedAt": "2026-07-07T03:26:58.377Z"
  },
  {
    "address": "0xDEMO_0006",
    "label": "TrendRider_7",
    "sourceRank": 7,
    "status": "track",
    "roi30d": 0.309,
    "consistencyScore": 0.818,
    "copyabilityScore": 0.823,
    "oneHitWonderPenalty": 0,
    "globalScore": 0.746,
    "bestCategory": "Crypto",
    "winRate30d": 0.544,
    "tradeCount30d": 745,
    "resolvedTradeCount30d": 372,
    "averageLiquidity": 1250.6700220277903,
    "averageSpread": 0.01701034633942875,
    "averageEntryTiming": 0.5966299180676977,
    "copyabilityNotes": "Good candidate — consistent, liquid, copyable",
    "riskNotes": null,
    "isDemo": true,
    "lastScannedAt": "2026-07-07T03:26:58.378Z"
  },
  {
    "address": "0xDEMO_0019",
    "label": "EdgeSeeker_20",
    "sourceRank": 20,
    "status": "track",
    "roi30d": 0.405,
    "consistencyScore": 0.835,
    "copyabilityScore": 0.626,
    "oneHitWonderPenalty": 0,
    "globalScore": 0.735,
    "bestCategory": "Sports",
    "winRate30d": 0.588,
    "tradeCount30d": 1379,
    "resolvedTradeCount30d": 689,
    "averageLiquidity": 2264.147569896043,
    "averageSpread": 0.04658312512038694,
    "averageEntryTiming": 0.5645337715060614,
    "copyabilityNotes": "Good candidate — consistent, liquid, copyable",
    "riskNotes": null,
    "isDemo": true,
    "lastScannedAt": "2026-07-07T03:26:58.378Z"
  },
  {
    "address": "0xDEMO_0007",
    "label": "ValueHunter_8",
    "sourceRank": 8,
    "status": "track",
    "roi30d": 0.297,
    "consistencyScore": 0.815,
    "copyabilityScore": 0.771,
    "oneHitWonderPenalty": 0,
    "globalScore": 0.732,
    "bestCategory": "Sports",
    "winRate30d": 0.538,
    "tradeCount30d": 948,
    "resolvedTradeCount30d": 474,
    "averageLiquidity": 2918.1497823660757,
    "averageSpread": 0.043249253660939554,
    "averageEntryTiming": 0.44162281957788024,
    "copyabilityNotes": "Good candidate — consistent, liquid, copyable",
    "riskNotes": null,
    "isDemo": true,
    "lastScannedAt": "2026-07-07T03:26:58.378Z"
  },
  {
    "address": "0xDEMO_0008",
    "label": "ProbPlayer_9",
    "sourceRank": 9,
    "status": "track",
    "roi30d": 0.21,
    "consistencyScore": 0.802,
    "copyabilityScore": 0.831,
    "oneHitWonderPenalty": 0,
    "globalScore": 0.719,
    "bestCategory": "Economics",
    "winRate30d": 0.505,
    "tradeCount30d": 2028,
    "resolvedTradeCount30d": 1014,
    "averageLiquidity": 1854.3233251361655,
    "averageSpread": 0.04867639868424871,
    "averageEntryTiming": 0.3573750439270088,
    "copyabilityNotes": "Good candidate — consistent, liquid, copyable",
    "riskNotes": null,
    "isDemo": true,
    "lastScannedAt": "2026-07-07T03:26:58.378Z"
  },
  {
    "address": "0xDEMO_0005",
    "label": "DataDriven_6",
    "sourceRank": 6,
    "status": "track",
    "roi30d": 0.371,
    "consistencyScore": 0.693,
    "copyabilityScore": 0.691,
    "oneHitWonderPenalty": 0,
    "globalScore": 0.704,
    "bestCategory": "Politics",
    "winRate30d": 0.571,
    "tradeCount30d": 55,
    "resolvedTradeCount30d": 27,
    "averageLiquidity": 1588.9264441194518,
    "averageSpread": 0.06752326299077875,
    "averageEntryTiming": 0.5341078798527434,
    "copyabilityNotes": "Good candidate — consistent, liquid, copyable",
    "riskNotes": null,
    "isDemo": true,
    "lastScannedAt": "2026-07-07T03:26:58.377Z"
  },
  {
    "address": "0xDEMO_0011",
    "label": "LogicBet_12",
    "sourceRank": 12,
    "status": "watch",
    "roi30d": 0.106,
    "consistencyScore": 0.785,
    "copyabilityScore": 0.839,
    "oneHitWonderPenalty": 0,
    "globalScore": 0.691,
    "bestCategory": "Politics",
    "winRate30d": 0.463,
    "tradeCount30d": 1483,
    "resolvedTradeCount30d": 741,
    "averageLiquidity": 1233.3243899072054,
    "averageSpread": 0.03388880263475425,
    "averageEntryTiming": 0.3731833180436602,
    "copyabilityNotes": "Monitor — needs more data or better spreads",
    "riskNotes": null,
    "isDemo": true,
    "lastScannedAt": "2026-07-07T03:26:58.378Z"
  },
  {
    "address": "0xDEMO_0013",
    "label": "ColdStart_14",
    "sourceRank": 14,
    "status": "watch",
    "roi30d": 0.075,
    "consistencyScore": 0.783,
    "copyabilityScore": 0.827,
    "oneHitWonderPenalty": 0,
    "globalScore": 0.68,
    "bestCategory": "Sports",
    "winRate30d": 0.458,
    "tradeCount30d": 1594,
    "resolvedTradeCount30d": 797,
    "averageLiquidity": 551.035782338427,
    "averageSpread": 0.04250159029390959,
    "averageEntryTiming": 0.49881435153692777,
    "copyabilityNotes": "Monitor — needs more data or better spreads",
    "riskNotes": null,
    "isDemo": true,
    "lastScannedAt": "2026-07-07T03:26:58.378Z"
  },
  {
    "address": "0xDEMO_0009",
    "label": "QuantMind_10",
    "sourceRank": 10,
    "status": "watch",
    "roi30d": 0.166,
    "consistencyScore": 0.797,
    "copyabilityScore": 0.648,
    "oneHitWonderPenalty": 0,
    "globalScore": 0.67,
    "bestCategory": "Science",
    "winRate30d": 0.493,
    "tradeCount30d": 713,
    "resolvedTradeCount30d": 356,
    "averageLiquidity": 932.3146622622207,
    "averageSpread": 0.06088517269037643,
    "averageEntryTiming": 0.40413636601568154,
    "copyabilityNotes": "Monitor — needs more data or better spreads",
    "riskNotes": null,
    "isDemo": true,
    "lastScannedAt": "2026-07-07T03:26:58.378Z"
  },
  {
    "address": "0xDEMO_0010",
    "label": "SwiftTrade_11",
    "sourceRank": 11,
    "status": "watch",
    "roi30d": 0.167,
    "consistencyScore": 0.795,
    "copyabilityScore": 0.646,
    "oneHitWonderPenalty": 0,
    "globalScore": 0.67,
    "bestCategory": "Pop Culture",
    "winRate30d": 0.488,
    "tradeCount30d": 673,
    "resolvedTradeCount30d": 336,
    "averageLiquidity": 3223.7770758116967,
    "averageSpread": 0.04117793357643037,
    "averageEntryTiming": 0.5265380876501855,
    "copyabilityNotes": "Monitor — needs more data or better spreads",
    "riskNotes": null,
    "isDemo": true,
    "lastScannedAt": "2026-07-07T03:26:58.378Z"
  },
  {
    "address": "0xDEMO_0014",
    "label": "NewHorizon_15",
    "sourceRank": 15,
    "status": "watch",
    "roi30d": 0.011,
    "consistencyScore": 0.772,
    "copyabilityScore": 0.829,
    "oneHitWonderPenalty": 0,
    "globalScore": 0.662,
    "bestCategory": "Economics",
    "winRate30d": 0.43,
    "tradeCount30d": 1494,
    "resolvedTradeCount30d": 747,
    "averageLiquidity": 2613.9109199062686,
    "averageSpread": 0.04994245194322929,
    "averageEntryTiming": 0.6288468001113983,
    "copyabilityNotes": "Monitor — needs more data or better spreads",
    "riskNotes": null,
    "isDemo": true,
    "lastScannedAt": "2026-07-07T03:26:58.378Z"
  },
  {
    "address": "0xDEMO_0012",
    "label": "RiskWise_13",
    "sourceRank": 13,
    "status": "watch",
    "roi30d": 0.073,
    "consistencyScore": 0.78,
    "copyabilityScore": 0.685,
    "oneHitWonderPenalty": 0,
    "globalScore": 0.65,
    "bestCategory": "Crypto",
    "winRate30d": 0.451,
    "tradeCount30d": 1506,
    "resolvedTradeCount30d": 753,
    "averageLiquidity": 1845.6562160745943,
    "averageSpread": 0.03563941761392038,
    "averageEntryTiming": 0.5862361803330405,
    "copyabilityNotes": "Monitor — needs more data or better spreads",
    "riskNotes": null,
    "isDemo": true,
    "lastScannedAt": "2026-07-07T03:26:58.378Z"
  }
]